trading_core/__init__.py
trading_core/py.typed
trading_core/types.py
trading_core_types-0.4.0.dist-info/METADATA
trading_core_types-0.4.0.dist-info/WHEEL
trading_core_types-0.4.0.dist-info/licenses/LICENSE
trading_core_types-0.4.0.dist-info/RECORD
