Metadata-Version: 2.4
Name: trading-core-types
Version: 0.4.0
Summary: Python implementation of trading-core types with Pydantic validation
Project-URL: Homepage, https://github.com/junduck/trading-core-types
Project-URL: Repository, https://github.com/junduck/trading-core-types
Project-URL: Issues, https://github.com/junduck/trading-core-types/issues
Author-email: Jun <imlijunda@gmail.com>
License: MIT License
License-File: LICENSE
Classifier: Development Status :: 4 - Beta
Classifier: Intended Audience :: Developers
Classifier: License :: OSI Approved :: MIT License
Classifier: Programming Language :: Python :: 3
Classifier: Programming Language :: Python :: 3.10
Classifier: Programming Language :: Python :: 3.11
Classifier: Programming Language :: Python :: 3.12
Classifier: Topic :: Software Development :: Libraries :: Python Modules
Requires-Python: >=3.10
Requires-Dist: pydantic>=2.0.0
Provides-Extra: dev
Requires-Dist: mypy>=1.0.0; extra == 'dev'
Requires-Dist: pytest>=8.0.0; extra == 'dev'
